Workbook

Sheet README
A1: Medicare Part D analyst pack (real CMS public data)
A3: Source: CMS data.cms.gov: Medicare Part D Spending by Drug (2020-2024), Medicare Monthly Enrollment, Part D Prescribers by Geography and Drug (2024), CMS 2026 negotiated-price fact sheet.
A4: Gross drug cost = Medicare + plan + beneficiary payments, before rebates. All of Part D, not one plan. Not UnitedHealth Group data.
A5: Blue cells are inputs copied from the CMS files by src/partd/excel_pack.py. Black cells are formulas. Yellow cells are assumptions you can change.
A6: Sheets: National_PMPM (per-member cost and a use-vs-price split), Drug_PVM (price/volume/mix by drug, 2023 to 2024), Negotiation (2026 prices and exposure),
A7: Net_Sensitivity (gross to net under an assumed rebate rate), State_PMPM (state comparison), Top_Drugs, Data_Checks.
A8: Known limits: dose units mix tablets, mL and pens; 2025 and Q1 2026 are preliminary and not used in growth rates; state cost is by prescriber location, enrollment by member residence.
A9: The rebate rate on Net_Sensitivity is an assumption, not a number from CMS data (CMS does not publish rebates).

Sheet National_PMPM
A1: National gross drug cost per member per month
A2: Inputs: CMS spending file (spend, claims) and CMS Monthly Enrollment (member months = Part D enrollees summed over 12 months).
A4: Year | B4: Gross spend ($) | C4: Claims | D4: Member months | E4: Gross PMPM ($) | F4: Claims per 1,000 member months | G4: Spend per claim ($) | H4: PMPM change vs prior year ($) | I4: PMPM change % | J4: Of which: claims per member ($) | K4: Of which: cost per claim ($) | L4: Split check
A5: 2020 | B5: 1.9409204e+11 | C5: 1454422165 | D5: 568957457 | E5: =B5/D5 -> 341.13629 | F5: =C5/D5*1000 -> 2556.2934 | G5: =B5/C5 -> 133.44959
A6: 2021 | B6: 2.1351335e+11 | C6: 1483268229 | D6: 585826189 | E6: =B6/D6 -> 364.46535 | F6: =C6/D6*1000 -> 2531.9254 | G6: =B6/C6 -> 143.9479 | H6: =E6-E5 -> 23.32906 | I6: =E6/E5-1 -> 0.068386332 | J6: =H6*LN(F6/F5)/(LN(F6/F5)+LN(G6/G5)) -> -3.377981 | K6: =H6*LN(G6/G5)/(LN(F6/F5)+LN(G6/G5)) -> 26.707041 | L6: =ROUND(J6+K6-H6,6) -> 0
A7: 2022 | B7: 2.3977922e+11 | C7: 1539211134 | D7: 603661158 | E7: =B7/D7 -> 397.20829 | F7: =C7/D7*1000 -> 2549.7932 | G7: =B7/C7 -> 155.78059 | H7: =E7-E6 -> 32.742935 | I7: =E7/E6-1 -> 0.089838265 | J7: =H7*LN(F7/F6)/(LN(F7/F6)+LN(G7/G6)) -> 2.6764757 | K7: =H7*LN(G7/G6)/(LN(F7/F6)+LN(G7/G6)) -> 30.066459 | L7: =ROUND(J7+K7-H7,6) -> 0
A8: 2023 | B8: 2.7580892e+11 | C8: 1616688565 | D8: 622842542 | E8: =B8/D8 -> 442.82286 | F8: =C8/D8*1000 -> 2595.6618 | G8: =B8/C8 -> 170.60114 | H8: =E8-E7 -> 45.614576 | I8: =E8/E7-1 -> 0.11483793 | J8: =H8*LN(F8/F7)/(LN(F8/F7)+LN(G8/G7)) -> 7.4811864 | K8: =H8*LN(G8/G7)/(LN(F8/F7)+LN(G8/G7)) -> 38.133389 | L8: =ROUND(J8+K8-H8,6) -> 0
A9: 2024 | B9: 2.8866784e+11 | C9: 1711657015 | D9: 652502372 | E9: =B9/D9 -> 442.40121 | F9: =C9/D9*1000 -> 2623.2196 | G9: =B9/C9 -> 168.64818 | H9: =E9-E8 -> -0.42164994 | I9: =E9/E8-1 -> -0.00095218646 | J9: =H9*LN(F9/F8)/(LN(F9/F8)+LN(G9/G8)) -> 4.6743923 | K9: =H9*LN(G9/G8)/(LN(F9/F8)+LN(G9/G8)) -> -5.0960422 | L9: =ROUND(J9+K9-H9,6) -> 0
A11: CAGR 2020-2024: PMPM | E11: =(E9/E5)^(1/(A9-A5))-1 -> 0.067141712
A12: CAGR: spend | B12: =(B9/B5)^(1/(A9-A5))-1 -> 0.10432695
A13: CAGR: claims | C13: =(C9/C5)^(1/(A9-A5))-1 -> 0.041553458
A15: Check: J + K equals H each year (should be 0)

Sheet Drug_PVM
A1: Price, volume and mix by drug, 2023 to 2024 (top 100 drugs by 2024 spend, all others combined)
A2: Volume = dose units. Method as in the dashboard: volume = (U1/U0-1)*S0; mix = (u1 - u0*U1/U0)*p0; price = u1*(p1-p0); new drugs = u1*p1. 'All other' is treated as one drug, so mix and price inside it are not shown; totals therefore differ from the dashboard's full drug-level split (dashboard: price about -$29B).
A4: Drug | B4: Spend 2023 ($) | C4: Dose units 2023 | D4: Spend 2024 ($) | E4: Dose units 2024 | F4: Price 2023 ($/unit) | G4: Price 2024 ($/unit) | H4: Volume effect ($) | I4: Mix effect ($) | J4: Price effect ($) | K4: New-drug effect ($) | L4: Total change ($) | M4: Check vs actual
A5: Eliquis | B5: 18273451967 | C5: 1.8752834e+09 | D5: 20774929225 | E5: 2.1562385e+09 | F5: =IF(C5>0,B5/C5,0) -> 9.7443681 | G5: =IF(E5>0,D5/E5,0) -> 9.634801 | H5: =IF(C5>0,(C5*($E$107/$C$107-1)*F5),0) -> 9.6040628e+08 | I5: =IF(C5>0,(E5-C5*$E$107/$C$107)*F5,0) -> 1.7773236e+09 | J5: =IF(AND(C5>0,E5>0),E5*(G5-F5),0) -> -2.3625265e+08 | K5: =IF(C5=0,D5,0) -> 0 | L5: =SUM(H5:K5) -> 2501477258 | M5: =ROUND(L5-(D5-B5),0) -> 0
A6: Ozempic | B6: 9.1940484e+09 | C6: 26990261 | D6: 12970296347 | E6: 42324233 | F6: =IF(C6>0,B6/C6,0) -> 340.64318 | G6: =IF(E6>0,D6/E6,0) -> 306.45083 | H6: =IF(C6>0,(C6*($E$107/$C$107-1)*F6),0) -> 4.8321586e+08 | I6: =IF(C6>0,(E6-C6*$E$107/$C$107)*F6,0) -> 4.7401969e+09 | J6: =IF(AND(C6>0,E6>0),E6*(G6-F6),0) -> -1.4471649e+09 | K6: =IF(C6=0,D6,0) -> 0 | L6: =SUM(H6:K6) -> 3.7762479e+09 | M6: =ROUND(L6-(D6-B6),0) -> 0
A7: Jardiance | B7: 8.8399351e+09 | C7: 4.352531e+08 | D7: 11435997421 | E7: 6.0418168e+08 | F7: =IF(C7>0,B7/C7,0) -> 20.309873 | G7: =IF(E7>0,D7/E7,0) -> 18.928077 | H7: =IF(C7>0,(C7*($E$107/$C$107-1)*F7),0) -> 4.6460456e+08 | I7: =IF(C7>0,(E7-C7*$E$107/$C$107)*F7,0) -> 2.9663135e+09 | J7: =IF(AND(C7>0,E7>0),E7*(G7-F7),0) -> -8.3485574e+08 | K7: =IF(C7=0,D7,0) -> 0 | L7: =SUM(H7:K7) -> 2.5960624e+09 | M7: =ROUND(L7-(D7-B7),0) -> 0
A8: Mounjaro | B8: 2.3613842e+09 | C8: 4374599.5 | D8: 6.3369426e+09 | E8: 12385380 | F8: =IF(C8>0,B8/C8,0) -> 539.79436 | G8: =IF(E8>0,D8/E8,0) -> 511.64703 | H8: =IF(C8>0,(C8*($E$107/$C$107-1)*F8),0) -> 1.2410836e+08 | I8: =IF(C8>0,(E8-C8*$E$107/$C$107)*F8,0) -> 4.2000655e+09 | J8: =IF(AND(C8>0,E8>0),E8*(G8-F8),0) -> -3.4861542e+08 | K8: =IF(C8=0,D8,0) -> 0 | L8: =SUM(H8:K8) -> 3.9755585e+09 | M8: =ROUND(L8-(D8-B8),0) -> 0
A9: Xarelto | B9: 6.3092468e+09 | C9: 3.5326709e+08 | D9: 6.2322318e+09 | E9: 3.6033752e+08 | F9: =IF(C9>0,B9/C9,0) -> 17.859707 | G9: =IF(E9>0,D9/E9,0) -> 17.29554 | H9: =IF(C9>0,(C9*($E$107/$C$107-1)*F9),0) -> 3.3159801e+08 | I9: =IF(C9>0,(E9-C9*$E$107/$C$107)*F9,0) -> -2.0532223e+08 | J9: =IF(AND(C9>0,E9>0),E9*(G9-F9),0) -> -2.0329076e+08 | K9: =IF(C9=0,D9,0) -> 0 | L9: =SUM(H9:K9) -> -77014983 | M9: =ROUND(L9-(D9-B9),0) -> 0
A10: Trulicity | B10: 7.3638562e+09 | C10: 15240416 | D10: 5.4541347e+09 | E10: 11660568 | F10: =IF(C10>0,B10/C10,0) -> 483.17946 | G10: =IF(E10>0,D10/E10,0) -> 467.74176 | H10: =IF(C10>0,(C10*($E$107/$C$107-1)*F10),0) -> 3.870256e+08 | I10: =IF(C10>0,(E10-C10*$E$107/$C$107)*F10,0) -> -2.1167347e+09 | J10: =IF(AND(C10>0,E10>0),E10*(G10-F10),0) -> -1.8001236e+08 | K10: =IF(C10=0,D10,0) -> 0 | L10: =SUM(H10:K10) -> -1.9097215e+09 | M10: =ROUND(L10-(D10-B10),0) -> 0
A11: Trelegy Ellipta | B11: 4.455884e+09 | C11: 3.9857917e+08 | D11: 5.2944018e+09 | E11: 5.0332468e+08 | F11: =IF(C11>0,B11/C11,0) -> 11.17942 | G11: =IF(E11>0,D11/E11,0) -> 10.51886 | H11: =IF(C11>0,(C11*($E$107/$C$107-1)*F11),0) -> 2.3418996e+08 | I11: =IF(C11>0,(E11-C11*$E$107/$C$107)*F11,0) -> 9.3680421e+08 | J11: =IF(AND(C11>0,E11>0),E11*(G11-F11),0) -> -3.324764e+08 | K11: =IF(C11=0,D11,0) -> 0 | L11: =SUM(H11:K11) -> 8.3851777e+08 | M11: =ROUND(L11-(D11-B11),0) -> 0
A12: Farxiga | B12: 4.3421823e+09 | C12: 222129205 | D12: 5.290549e+09 | E12: 2.8886603e+08 | F12: =IF(C12>0,B12/C12,0) -> 19.548003 | G12: =IF(E12>0,D12/E12,0) -> 18.314888 | H12: =IF(C12>0,(C12*($E$107/$C$107-1)*F12),0) -> 2.2821409e+08 | I12: =IF(C12>0,(E12-C12*$E$107/$C$107)*F12,0) -> 1.0763575e+09 | J12: =IF(AND(C12>0,E12>0),E12*(G12-F12),0) -> -3.5620496e+08 | K12: =IF(C12=0,D12,0) -> 0 | L12: =SUM(H12:K12) -> 9.4836666e+08 | M12: =ROUND(L12-(D12-B12),0) -> 0
A13: Humira(Cf) Pen | B13: 4.4198282e+09 | C13: 1182524.4 | D13: 4.3286989e+09 | E13: 1229464.9 | F13: =IF(C13>0,B13/C13,0) -> 3737.6211 | G13: =IF(E13>0,D13/E13,0) -> 3520.7989 | H13: =IF(C13>0,(C13*($E$107/$C$107-1)*F13),0) -> 2.3229496e+08 | I13: =IF(C13>0,(E13-C13*$E$107/$C$107)*F13,0) -> -56849004 | J13: =IF(AND(C13>0,E13>0),E13*(G13-F13),0) -> -2.6657528e+08 | K13: =IF(C13=0,D13,0) -> 0 | L13: =SUM(H13:K13) -> -91129324 | M13: =ROUND(L13-(D13-B13),0) -> 0
A14: Revlimid | B14: 3.8598048e+09 | C14: 4395154 | D14: 4.1795115e+09 | E14: 4888867 | F14: =IF(C14>0,B14/C14,0) -> 878.19557 | G14: =IF(E14>0,D14/E14,0) -> 854.9039 | H14: =IF(C14>0,(C14*($E$107/$C$107-1)*F14),0) -> 2.0286155e+08 | I14: =IF(C14>0,(E14-C14*$E$107/$C$107)*F14,0) -> 2.3071502e+08 | J14: =IF(AND(C14>0,E14>0),E14*(G14-F14),0) -> -1.1386987e+08 | K14: =IF(C14=0,D14,0) -> 0 | L14: =SUM(H14:K14) -> 3.197067e+08 | M14: =ROUND(L14-(D14-B14),0) -> 0
A15: Entresto | B15: 3.4304416e+09 | C15: 2.9465348e+08 | D15: 4.0203217e+09 | E15: 3.6416628e+08 | F15: =IF(C15>0,B15/C15,0) -> 11.642291 | G15: =IF(E15>0,D15/E15,0) -> 11.039797 | H15: =IF(C15>0,(C15*($E$107/$C$107-1)*F15),0) -> 1.8029531e+08 | I15: =IF(C15>0,(E15-C15*$E$107/$C$107)*F15,0) -> 6.2899305e+08 | J15: =IF(AND(C15>0,E15>0),E15*(G15-F15),0) -> -2.1940826e+08 | K15: =IF(C15=0,D15,0) -> 0 | L15: =SUM(H15:K15) -> 5.898801e+08 | M15: =ROUND(L15-(D15-B15),0) -> 0
A16: Januvia | B16: 4.0908368e+09 | C16: 2.1668559e+08 | D16: 3.8078547e+09 | E16: 2.119843e+08 | F16: =IF(C16>0,B16/C16,0) -> 18.879137 | G16: =IF(E16>0,D16/E16,0) -> 17.962909 | H16: =IF(C16>0,(C16*($E$107/$C$107-1)*F16),0) -> 2.1500401e+08 | I16: =IF(C16>0,(E16-C16*$E$107/$C$107)*F16,0) -> -3.0376028e+08 | J16: =IF(AND(C16>0,E16>0),E16*(G16-F16),0) -> -1.9422589e+08 | K16: =IF(C16=0,D16,0) -> 0 | L16: =SUM(H16:K16) -> -2.8298216e+08 | M16: =ROUND(L16-(D16-B16),0) -> 0
... A105: All other drugs | B105: 1.0527807e+11 | C105: 1.1357205e+11 | D105: 9.5828473e+10 | E105: 1.1888904e+11 | F105: =IF(C105>0,B105/C105,0) -> 0.92697162 | G105: =IF(E105>0,D105/E105,0) -> 0.80603288 | H105: =IF(C105>0,(C105*($E$107/$C$107-1)*F105),0) -> 5.5331482e+09 | I105: =IF(C105>0,(E105-C105*$E$107/$C$107)*F105,0) -> -6.0445163e+08 | J105: =IF(AND(C105>0,E105>0),E105*(G105-F105),0) -> -1.4378291e+10 | K105: =IF(C105=0,D105,0) -> 0 | L105: =SUM(H105:K105) -> -9.4495942e+09 | M105: =ROUND(L105-(D105-B105),0) -> 0
A107: Total | B107: =SUM(B5:B105) -> 2.7580892e+11 | C107: =SUM(C5:C105) -> 1.2466047e+11 | D107: =SUM(D5:D105) -> 2.8866784e+11 | E107: =SUM(E5:E105) -> 1.3121231e+11 | H107: =SUM(H5:H105) -> 1.4495817e+10 | I107: =SUM(I5:I105) -> 2.306961e+10 | J107: =SUM(J5:J105) -> -2.4706504e+10 | K107: =SUM(K5:K105) -> 0 | L107: =SUM(L5:L105) -> 1.2858923e+10 | M107: =SUM(M5:M105) -> 0
A109: Share of total change: price | J109: =J107/L107 -> -1.9213509
A110: Share of total change: volume + mix | J110: =(H107+I107)/L107 -> 2.9213509
A112: Note: row totals use drug-level volume/mix at each drug's own prior price; the identity (column M) should read 0 on every row.

Sheet Negotiation
A1: Medicare negotiated prices for 2026 (first 10 drugs): exposure and early check
A2: List and negotiated prices (30-day) transcribed from the CMS fact sheet: https://cms.gov/files/document/fact-sheet-negotiated-prices-initial-price-applicability-year-2026.pdf
A4: Drug | B4: List price, 30 days ($) | C4: Negotiated price, 30 days ($) | D4: Cut | E4: 2024 gross spend ($) | F4: Share of 2024 Part D spend | G4: Cut applied to 2024 spend ($) | H4: Spend per claim 2025 ($) | I4: Spend per claim Q1 2026 ($) | J4: Observed change
A5: Eliquis | B5: 521 | C5: 231 | D5: =1-C5/B5 -> 0.55662188 | E5: 20774929225 | F5: =E5/National_PMPM!$B$9 -> 0.071968284 | G5: =E5*D5 -> 1.156378e+10 | H5: 912.3142 | I5: 399.01009 | J5: =I5/H5-1 -> -0.56263962
A6: Jardiance | B6: 573 | C6: 197 | D6: =1-C6/B6 -> 0.65619546 | E6: 11435997421 | F6: =E6/National_PMPM!$B$9 -> 0.039616458 | G6: =E6*D6 -> 7.5042496e+09 | H6: 1091.1936 | I6: 386.82923 | J6: =I6/H6-1 -> -0.645499
A7: Xarelto | B7: 517 | C7: 197 | D7: =1-C7/B7 -> 0.61895551 | E7: 6.2322318e+09 | F7: =E7/National_PMPM!$B$9 -> 0.02158963 | G7: =E7*D7 -> 3.8574743e+09 | H7: 1006.2108 | I7: 374.03804 | J7: =I7/H7-1 -> -0.62827071
A8: Farxiga | B8: 556 | C8: 178.5 | D8: =1-C8/B8 -> 0.67895683 | E8: 5.290549e+09 | F8: =E8/National_PMPM!$B$9 -> 0.018327462 | G8: =E8*D8 -> 3.5920544e+09 | H8: 997.75093 | I8: 328.9655 | J8: =I8/H8-1 -> -0.67029297
A9: Entresto | B9: 628 | C9: 295 | D9: =1-C9/B9 -> 0.53025478 | E9: 4.0204664e+09 | F9: =E9/National_PMPM!$B$9 -> 0.013927656 | G9: =E9*D9 -> 2.1318715e+09 | H9: 1077.5611 | I9: 323.74029 | J9: =I9/H9-1 -> -0.69956201
A10: Januvia | B10: 527 | C10: 113 | D10: =1-C10/B10 -> 0.78557875 | E10: 3.8078547e+09 | F10: =E10/National_PMPM!$B$9 -> 0.013191129 | G10: =E10*D10 -> 2.9913697e+09 | H10: 556.07545 | I10: 214.01208 | J10: =I10/H10-1 -> -0.61513842
A11: Stelara | B11: 13836 | C11: 4695 | D11: =1-C11/B11 -> 0.66066782 | E11: 3.3780174e+09 | F11: =E11/National_PMPM!$B$9 -> 0.011702091 | G11: =E11*D11 -> 2.2317474e+09 | H11: 26682.004 | I11: 8424.8196 | J11: =I11/H11-1 -> -0.68425087
A12: Enbrel | B12: 7106 | C12: 2355 | D12: =1-C12/B12 -> 0.66858992 | E12: 3.2255679e+09 | F12: =E12/National_PMPM!$B$9 -> 0.011173977 | G12: =E12*D12 -> 2.1565822e+09 | H12: 8681.6348 | I12: 2536.7401 | J12: =I12/H12-1 -> -0.70780387
A13: Imbruvica | B13: 14934 | C13: 9319 | D13: =1-C13/B13 -> 0.37598768 | E13: 2.266252e+09 | F13: =E13/National_PMPM!$B$9 -> 0.0078507256 | G13: =E13*D13 -> 8.5208284e+08 | H13: 16055.462 | I13: 9646.3037 | J13: =I13/H13-1 -> -0.39918864
A14: Fiasp/NovoLog | B14: 495 | C14: 119 | D14: =1-C14/B14 -> 0.75959596 | E14: 7.6542837e+08 | F14: =E14/National_PMPM!$B$9 -> 0.0026515886 | G14: =E14*D14 -> 5.8141629e+08 | H14: 293.80347 | I14: 204.41641 | J14: =I14/H14-1 -> -0.30424101
A15: Total | E15: =SUM(E5:E14) -> 6.1197294e+10 | F15: =SUM(F5:F14) -> 0.211999 | G15: =SUM(G5:G14) -> 3.7462628e+10
A17: Cut as % of these drugs' spend | G17: =G15/E15 -> 0.61216152
A18: Per member per month at 2024 volume ($) | G18: =G15/National_PMPM!$D$9 -> 57.413781
A20: Constant-volume, gross, vs list: a ceiling, not a forecast. Rebates already paid on these drugs make the plan's net effect smaller. NovoLog's list price was already cut in 2024, so its observed drop is small.

Sheet Net_Sensitivity
A1: Gross to net: what an assumed rebate rate does to cost per member per month
A2: CMS does not publish rebates. The rate below is an ASSUMPTION for illustration, not a number from the data. Change the yellow cell.
A4: Assumed rebate rate (share of gross spend) | B4: 0.2
A5: 2024 gross PMPM ($) | B5: =National_PMPM!E9 -> 442.40121
A6: Implied net PMPM ($) | B6: =B5*(1-B4) -> 353.92097
A7: Implied net 2024 spend ($) | B7: =National_PMPM!B9*(1-B4) -> 2.3093427e+11
A9: Rebate rate | B9: Net PMPM ($) | C9: Net 2024 spend ($)
A10: 0 | B10: =$B$5*(1-A10) -> 442.40121 | C10: =National_PMPM!$B$9*(1-A10) -> 2.8866784e+11
A11: 0.05 | B11: =$B$5*(1-A11) -> 420.28115 | C11: =National_PMPM!$B$9*(1-A11) -> 2.7423445e+11
A12: 0.1 | B12: =$B$5*(1-A12) -> 398.16109 | C12: =National_PMPM!$B$9*(1-A12) -> 2.5980106e+11
A13: 0.15 | B13: =$B$5*(1-A13) -> 376.04103 | C13: =National_PMPM!$B$9*(1-A13) -> 2.4536767e+11
A14: 0.2 | B14: =$B$5*(1-A14) -> 353.92097 | C14: =National_PMPM!$B$9*(1-A14) -> 2.3093427e+11
A15: 0.25 | B15: =$B$5*(1-A15) -> 331.80091 | C15: =National_PMPM!$B$9*(1-A15) -> 2.1650088e+11
A16: 0.3 | B16: =$B$5*(1-A16) -> 309.68085 | C16: =National_PMPM!$B$9*(1-A16) -> 2.0206749e+11
A17: 0.35 | B17: =$B$5*(1-A17) -> 287.56079 | C17: =National_PMPM!$B$9*(1-A17) -> 1.876341e+11
A18: 0.4 | B18: =$B$5*(1-A18) -> 265.44073 | C18: =National_PMPM!$B$9*(1-A18) -> 1.7320071e+11

Sheet State_PMPM
A1: Gross drug cost per member per month by state, 2024
A2: Cost is by prescriber location; member months by residence. DC is inflated by cross-border prescribing. Territories excluded.
A4: State | B4: Gross spend ($) | C4: Member months | D4: 30-day fills | E4: Gross PMPM ($) | F4: vs national | G4: Rank (1 = highest) | H4: Fills per member per month | I4: Cost per fill ($)
A5: AK | B5: 3.9628787e+08 | C5: 961563 | D5: 3516798.5 | E5: =B5/C5 -> 412.12887 | F5: =E5/National_PMPM!$E$9-1 -> -0.068427364 | G5: =RANK(E5,$E$5:$E$55) -> 27 | H5: =D5/C5 -> 3.6573771 | I5: =B5/D5 -> 112.68427
A6: AL | B6: 5.3415928e+09 | C6: 10653433 | D6: 58393682 | E6: =B6/C6 -> 501.39638 | F6: =E6/National_PMPM!$E$9-1 -> 0.13335218 | G6: =RANK(E6,$E$5:$E$55) -> 7 | H6: =D6/C6 -> 5.481208 | I6: =B6/D6 -> 91.475526
A7: AR | B7: 2.6956935e+09 | C7: 6417333 | D7: 33447076 | E7: =B7/C7 -> 420.06445 | F7: =E7/National_PMPM!$E$9-1 -> -0.050489825 | G7: =RANK(E7,$E$5:$E$55) -> 26 | H7: =D7/C7 -> 5.2119901 | I7: =B7/D7 -> 80.59579
A8: AZ | B8: 5.351741e+09 | C8: 14343030 | D8: 60476871 | E8: =B8/C8 -> 373.12486 | F8: =E8/National_PMPM!$E$9-1 -> -0.1565917 | G8: =RANK(E8,$E$5:$E$55) -> 39 | H8: =D8/C8 -> 4.2164641 | I8: =B8/D8 -> 88.492359
A9: CA | B9: 2.7329194e+10 | C9: 69123219 | D9: 2.8980216e+08 | E9: =B9/C9 -> 395.36923 | F9: =E9/National_PMPM!$E$9-1 -> -0.1063107 | G9: =RANK(E9,$E$5:$E$55) -> 32 | H9: =D9/C9 -> 4.1925443 | I9: =B9/D9 -> 94.302935
A10: CO | B10: 3.6970909e+09 | C10: 9896428 | D10: 39765645 | E10: =B10/C10 -> 373.57831 | F10: =E10/National_PMPM!$E$9-1 -> -0.15556671 | G10: =RANK(E10,$E$5:$E$55) -> 38 | H10: =D10/C10 -> 4.0181816 | I10: =B10/D10 -> 92.971984
A11: CT | B11: 4.1041291e+09 | C11: 7458155 | D11: 37183440 | E11: =B11/C11 -> 550.28745 | F11: =E11/National_PMPM!$E$9-1 -> 0.24386515 | G11: =RANK(E11,$E$5:$E$55) -> 3 | H11: =D11/C11 -> 4.9856083 | I11: =B11/D11 -> 110.37519
A12: DC | B12: 7.1608634e+08 | C12: 852257 | D12: 4644670.2 | E12: =B12/C12 -> 840.22347 | F12: =E12/National_PMPM!$E$9-1 -> 0.8992341 | G12: =RANK(E12,$E$5:$E$55) -> 1 | H12: =D12/C12 -> 5.4498469 | I12: =B12/D12 -> 154.17377
A13: DE | B13: 9.4060782e+08 | C13: 2371271 | D13: 10464734 | E13: =B13/C13 -> 396.66821 | F13: =E13/National_PMPM!$E$9-1 -> -0.1033745 | G13: =RANK(E13,$E$5:$E$55) -> 31 | H13: =D13/C13 -> 4.413133 | I13: =B13/D13 -> 89.883583
A14: FL | B14: 2.1460947e+10 | C14: 50517563 | D14: 2.4990352e+08 | E14: =B14/C14 -> 424.8215 | F14: =E14/National_PMPM!$E$9-1 -> -0.039737045 | G14: =RANK(E14,$E$5:$E$55) -> 24 | H14: =D14/C14 -> 4.9468642 | I14: =B14/D14 -> 85.876927
A15: GA | B15: 9.1472898e+09 | C15: 18582235 | D15: 96712227 | E15: =B15/C15 -> 492.25994 | F15: =E15/National_PMPM!$E$9-1 -> 0.11270024 | G15: =RANK(E15,$E$5:$E$55) -> 9 | H15: =D15/C15 -> 5.204553 | I15: =B15/D15 -> 94.582558
A16: HI | B16: 997311911 | C16: 2754909 | D16: 9720544.1 | E16: =B16/C16 -> 362.01265 | F16: =E16/National_PMPM!$E$9-1 -> -0.18170964 | G16: =RANK(E16,$E$5:$E$55) -> 43 | H16: =D16/C16 -> 3.5284447 | I16: =B16/D16 -> 102.59836
... A55: WY | B55: 2.586537e+08 | C55: 1099499 | D55: 3924191.4 | E55: =B55/C55 -> 235.24687 | F55: =E55/National_PMPM!$E$9-1 -> -0.46824995 | G55: =RANK(E55,$E$5:$E$55) -> 51 | H55: =D55/C55 -> 3.5690723 | I55: =B55/D55 -> 65.91261

Sheet Top_Drugs
A1: Top 25 drugs by 2024 gross spend
A3: Rank | B3: Drug | C3: Spend 2020 ($) | D3: Spend 2024 ($) | E3: Share of 2024 | F3: Cumulative share | G3: Change 2020-2024 ($) | H3: Claims 2024 | I3: Spend per claim 2024 ($)
A4: 1 | B4: Eliquis | C4: 9.9360698e+09 | D4: 20774929225 | E4: =D4/National_PMPM!$B$9 -> 0.071968284 | F4: =SUM($E$4:E4) -> 0.071968284 | G4: =D4-C4 -> 1.0838859e+10 | H4: 24061332 | I4: =D4/H4 -> 863.41559
A5: 2 | B5: Ozempic | C5: 1.4558123e+09 | D5: 12970296347 | E5: =D5/National_PMPM!$B$9 -> 0.04493156 | F5: =SUM($E$4:E5) -> 0.11689984 | G5: =D5-C5 -> 1.1514484e+10 | H5: 10417182 | I5: =D5/H5 -> 1245.0869
A6: 3 | B6: Jardiance | C6: 2.3761663e+09 | D6: 11435997421 | E6: =D6/National_PMPM!$B$9 -> 0.039616458 | F6: =SUM($E$4:E6) -> 0.1565163 | G6: =D6-C6 -> 9.0598311e+09 | H6: 11368280 | I6: =D6/H6 -> 1005.9567
A7: 4 | B7: Mounjaro | C7: 0 | D7: 6.3369426e+09 | E7: =D7/National_PMPM!$B$9 -> 0.021952368 | F7: =SUM($E$4:E7) -> 0.17846867 | G7: =D7-C7 -> 6.3369426e+09 | H7: 5105397 | I7: =D7/H7 -> 1241.2243
A8: 5 | B8: Xarelto | C8: 4701314805 | D8: 6.2322318e+09 | E8: =D8/National_PMPM!$B$9 -> 0.02158963 | F8: =SUM($E$4:E8) -> 0.2000583 | G8: =D8-C8 -> 1.530917e+09 | H8: 6660246 | I8: =D8/H8 -> 935.73598
A9: 6 | B9: Trulicity | C9: 3.2848731e+09 | D9: 5.4541347e+09 | E9: =D9/National_PMPM!$B$9 -> 0.018894154 | F9: =SUM($E$4:E9) -> 0.21895245 | G9: =D9-C9 -> 2.1692617e+09 | H9: 4305141 | I9: =D9/H9 -> 1266.8888
A10: 7 | B10: Trelegy Ellipta | C10: 1.4878023e+09 | D10: 5.2944018e+09 | E10: =D10/National_PMPM!$B$9 -> 0.018340809 | F10: =SUM($E$4:E10) -> 0.23729326 | G10: =D10-C10 -> 3.8065995e+09 | H10: 6250872 | I10: =D10/H10 -> 846.98611
A11: 8 | B11: Farxiga | C11: 7.3678756e+08 | D11: 5.290549e+09 | E11: =D11/National_PMPM!$B$9 -> 0.018327462 | F11: =SUM($E$4:E11) -> 0.25562072 | G11: =D11-C11 -> 4.5537614e+09 | H11: 5634650 | I11: =D11/H11 -> 938.93125
A12: 9 | B12: Humira(Cf) Pen | C12: 2.1694304e+09 | D12: 4.3286989e+09 | E12: =D12/National_PMPM!$B$9 -> 0.014995432 | F12: =SUM($E$4:E12) -> 0.27061616 | G12: =D12-C12 -> 2.1592684e+09 | H12: 490303 | I12: =D12/H12 -> 8828.62
A13: 10 | B13: Revlimid | C13: 5.3560503e+09 | D13: 4.1795115e+09 | E13: =D13/National_PMPM!$B$9 -> 0.014478618 | F13: =SUM($E$4:E13) -> 0.28509477 | G13: =D13-C13 -> -1.1765388e+09 | H13: 239843 | I13: =D13/H13 -> 17426.031
A14: 11 | B14: Entresto | C14: 1203043540 | D14: 4.0203217e+09 | E14: =D14/National_PMPM!$B$9 -> 0.013927155 | F14: =SUM($E$4:E14) -> 0.29902193 | G14: =D14-C14 -> 2.8172781e+09 | H14: 3898804 | I14: =D14/H14 -> 1031.1679
A15: 12 | B15: Januvia | C15: 3.8650878e+09 | D15: 3.8078547e+09 | E15: =D15/National_PMPM!$B$9 -> 0.013191129 | F15: =SUM($E$4:E15) -> 0.31221306 | G15: =D15-C15 -> -57233111 | H15: 4027317 | I15: =D15/H15 -> 945.50656
... A28: 25 | B28: Linzess | C28: 1.1444681e+09 | D28: 1.9819586e+09 | E28: =D28/National_PMPM!$B$9 -> 0.0068658795 | F28: =SUM($E$4:E28) -> 0.42633502 | G28: =D28-C28 -> 8.374905e+08 | H28: 2506531 | I28: =D28/H28 -> 790.71778

Sheet Data_Checks
A1: Cross-file reconciliation
A3: Check | B3: A | C3: B | D3: Difference | E3: Tolerance | F3: Result
A4: Spending-by-drug 2024 total vs prescriber-file national total | B4: 2.8866784e+11 | C4: 2.8856968e+11 | D4: =IF(B4=0,0,C4/B4-1) -> -0.00034006663 | E4: 0.005 | F4: =IF(ABS(D4)<=E4,"pass","FAIL") -> pass
A5: Prescriber-file national total vs sum of states | B5: 2.8856968e+11 | C5: 2.880192e+11 | D5: =IF(B5=0,0,C5/B5-1) -> -0.0019075876 | E5: 0.01 | F5: =IF(ABS(D5)<=E5,"pass","FAIL") -> pass
A6: Part D enrollees: PDP + MA-PD = total (Dec 2024) | B6: 54807408 | C6: 54807408 | D6: =IF(B6=0,0,C6/B6-1) -> 0 | E6: 0.001 | F6: =IF(ABS(D6)<=E6,"pass","FAIL") -> pass
A7: Drug rows with CMS outlier flag, 2024 (share of rows) | B7: 395 | C7: 3625 | D7: =B7/C7 -> 0.10896552 | E7: info | F7: info
A8: Drug rows with spend but zero claims, 2024 | B8: 0 | C8: 0 | D8: =B8-C8 -> 0 | E8: 0 | F8: =IF(D8=E8,"pass","FAIL") -> pass
